{"cameraMode":{"drawMode":0,"name":"Shaded","section":"Shading Mode"},"sceneLighting":true,"audioPlay":false,"sceneViewState":{"m_AlwaysRefresh":false,"showFog":true,"showSkybox":true,"showFlares":true,"showImageEffects":true,"showParticleSystems":true,"showVisualEffectGraphs":true,"m_FxEnabled":true},"in2DMode":false,"pivot":{"x":-0.7913216352462769,"y":-0.8267183303833008,"z":-0.1191588044166565},"rotation":{"x":0.005627241916954517,"y":0.7961642742156982,"z":-0.6050086617469788,"w":0.00740523636341095},"size":3.909517765045166,"orthographic":false}